vvar/__init__.py
vvar/vvar.py
vvar-0.5.dist-info/LICENSE
vvar-0.5.dist-info/METADATA
vvar-0.5.dist-info/WHEEL
vvar-0.5.dist-info/top_level.txt
vvar-0.5.dist-info/RECORD
