Metadata-Version: 2.1
Name: vvar
Version: 0.5
Summary: Virtual user-persistent variables, accessible via an environment object
Home-page: https://github.com/swip3798/vvar
Author: Christian Schweigel
Author-email: 
License: UNKNOWN
Platform: UNKNOWN
Classifier: Programming Language :: Python :: 3
Classifier: Programming Language :: Python :: 3 :: Only
Classifier: License :: OSI Approved :: MIT License
Classifier: Operating System :: OS Independent
Classifier: Development Status :: 3 - Alpha
